LICENSE
MANIFEST.in
README.md
requirements.txt
setup.py
src/nicestudio/__init__.py
src/nicestudio.pvetools.egg-info/PKG-INFO
src/nicestudio.pvetools.egg-info/SOURCES.txt
src/nicestudio.pvetools.egg-info/dependency_links.txt
src/nicestudio.pvetools.egg-info/entry_points.txt
src/nicestudio.pvetools.egg-info/not-zip-safe
src/nicestudio.pvetools.egg-info/requires.txt
src/nicestudio.pvetools.egg-info/top_level.txt
src/nicestudio/pvetools/__init__.py
src/nicestudio/pvetools/bases.py
src/nicestudio/pvetools/main.py
src/nicestudio/pvetools/utils.py
src/nicestudio/pvetools/commands/__init__.py
src/nicestudio/pvetools/commands/vm.py